conti/__init__.py
conti/common.py
conti/encoder.py
conti/filters.py
conti/probe.py
conti/source.py
conti/utils.py
conti-1.0.dist-info/entry_points.txt
conti-1.0.dist-info/LICENSE.md
conti-1.0.dist-info/WHEEL
conti-1.0.dist-info/METADATA
conti-1.0.dist-info/RECORD
