Metadata-Version: 2.1
Name: conti
Version: 1.0
Summary: Minimalistic FFMpeg based playout server
Home-page: https://github.com/immstudios/conti
License: MIT
Keywords: playout,broadcast,streaming,ffmpeg,television
Author: Martin Wacker
Author-email: martas@imm.cz
Requires-Python: >=3.6,<4.0
Classifier: Development Status :: 5 - Production/Stable
Classifier: Environment :: Console
Classifier: Intended Audience :: Developers
Classifier: License :: OSI Approved :: MIT License
Classifier: Natural Language :: English
Classifier: Operating System :: POSIX :: Linux
Classifier: Programming Language :: Python
Classifier: Programming Language :: Python :: 3
Classifier: Programming Language :: Python :: 3.6
Classifier: Programming Language :: Python :: 3.7
Classifier: Programming Language :: Python :: 3.8
Classifier: Programming Language :: Python :: 3.9
Classifier: Topic :: Multimedia :: Video :: Conversion
Requires-Dist: nxtools (>=1.6.0,<2.0.0)
Project-URL: Repository, https://github.com/immstudios/conti
